currencyconverterbelbot/__init__.py
currencyconverterbelbot/bot.py
currencyconverterbelbot-1.0.0.dist-info/WHEEL
currencyconverterbelbot-1.0.0.dist-info/METADATA
currencyconverterbelbot-1.0.0.dist-info/RECORD
