Metadata-Version: 2.1
Name: currencyconverterbelbot
Version: 1.0.0
Summary: 
Author: andrei
Author-email: dorofeichik9723@gmail.com
Requires-Python: >=3.8,<4.0
Classifier: Programming Language :: Python :: 3
Classifier: Programming Language :: Python :: 3.10
Classifier: Programming Language :: Python :: 3.8
Classifier: Programming Language :: Python :: 3.9
Requires-Dist: aiogram (>=2.21,<3.0)
Requires-Dist: black (>=22.6.0,<23.0.0)
Requires-Dist: bs4 (>=0.0.1,<0.0.2)
Requires-Dist: lxml (>=4.9.1,<5.0.0)
Requires-Dist: requests (>=2.28.1,<3.0.0)
